config.yaml
pyproject.toml
stack_exchange/__init__.py
stack_exchange/__main__.py
stack_exchange/_version.py
stack_exchange/app.py
stack_exchange/cache.py
stack_exchange/cli.py
stack_exchange/commands.py
stack_exchange/errors.py
stack_exchange/models.py
stack_exchange/search.py
stack_exchange/utils.py
stack_exchange_cli-1.0.0.dist-info/entry_points.txt
stack_exchange_cli-1.0.0.dist-info/LICENSE
stack_exchange_cli-1.0.0.dist-info/WHEEL
stack_exchange_cli-1.0.0.dist-info/METADATA
stack_exchange_cli-1.0.0.dist-info/RECORD
