Metadata-Version: 2.1
Name: stack-exchange-cli
Version: 1.0.0
Summary: Stack Exchange CLI for searching
License: MIT
Keywords: stack-exchange,stack-exchange search,stack-exchange cli,stackoverflow,stackexchange
Author: Mike Davidson
Requires-Python: >=3.10,<4.0
Classifier: License :: OSI Approved :: MIT License
Classifier: Programming Language :: Python :: 3
Classifier: Programming Language :: Python :: 3.10
Requires-Dist: PyYAML (>=6.0,<7.0)
Requires-Dist: markdownify (>=0.11.2,<0.12.0)
Requires-Dist: redis (>=4.3.4,<5.0.0)
Requires-Dist: requests (>=2.28.0,<3.0.0)
Requires-Dist: rich (>=12.4.4,<13.0.0)
Requires-Dist: toml (>=0.10.2,<0.11.0)
